minigc/__init__.py
minigc/consoleframe.py
minigc/main.py
minigc/topframe.py
minigc/uavnode.py
minigc/config/minidrone_config.yaml
minigc/config/minidrone_show_config.yaml
minigc/image/minidrone-logo.png
minigc/image/off.png
minigc/image/on.png
minigc/launch/linktrack.launch
minigc/launch/mavros.launch
minigc-1.0.dist-info/LICENSE
minigc-1.0.dist-info/METADATA
minigc-1.0.dist-info/WHEEL
minigc-1.0.dist-info/entry_points.txt
minigc-1.0.dist-info/top_level.txt
minigc-1.0.dist-info/RECORD
